zerophone_hw.py
zerophone_hw-0.4.4.dist-info/LICENSE
zerophone_hw-0.4.4.dist-info/METADATA
zerophone_hw-0.4.4.dist-info/WHEEL
zerophone_hw-0.4.4.dist-info/entry_points.txt
zerophone_hw-0.4.4.dist-info/top_level.txt
zerophone_hw-0.4.4.dist-info/RECORD
