Metadata-Version: 2.1
Name: zerophone-hw
Version: 0.4.4
Summary: ZeroPhone low-level API library. Not to be used by users directly! Is only intended for low-level framework developers and as a hardware reference.
Home-page: https://github.com/ZeroPhone/Zerophone-LowLevel-API-Python
Author: CRImier
Author-email: crimier@yandex.ru
License: UNKNOWN
Download-URL: https://github.com/ZeroPhone/zerophone-lowlevel-api-python/archive/0.4.4.tar.gz
Platform: UNKNOWN
Requires-Dist: gpio
